server.py
backend/__init__.py
backend/app.py
backend/config.py
backend/feedback_handler.py
backend/port_info.py
backend/server.py
backend/server_manager.py
backend/server_pool.py
backend/type_definitions.py
backend/version.py
backend/request_processing/__init__.py
backend/request_processing/data_extractors.py
backend/request_processing/validators.py
backend/routes/__init__.py
backend/routes/feedback_routes.py
backend/security/__init__.py
backend/security/csrf_handler.py
backend/static/css/styles.css
backend/static/css/websocket-status.css
backend/static/js/modules/README.md
backend/static/js/modules/error-handler.js
backend/static/js/modules/form-handler.js
backend/static/js/modules/image-handler.js
backend/static/js/modules/markdown-renderer.js
backend/static/js/modules/suggestion-handler.js
backend/static/js/modules/ui-status-manager.js
backend/static/js/modules/utils.js
backend/static/js/modules/websocket-manager.js
backend/templates/feedback.html
backend/utils/__init__.py
backend/utils/browser_utils.py
backend/utils/custom_exceptions.py
backend/utils/format_utils.py
backend/utils/image_utils.py
backend/utils/logging_utils.py
backend/utils/network_utils.py
backend/utils/static_cache.py
mcp_feedback_pipe-3.0.15.dist-info/licenses/LICENSE
mcp_feedback_pipe-3.0.15.dist-info/METADATA
mcp_feedback_pipe-3.0.15.dist-info/WHEEL
mcp_feedback_pipe-3.0.15.dist-info/entry_points.txt
mcp_feedback_pipe-3.0.15.dist-info/top_level.txt
mcp_feedback_pipe-3.0.15.dist-info/RECORD
