Metadata-Version: 2.4
Name: mcp-feedback-pipe
Version: 3.0.15
Summary: A modern Web-based MCP server for interactive user feedback collection - perfect for SSH environments
Author-email: ElemTran <your.email@example.com>
Maintainer-email: ElemTran <your.email@example.com>
License: MIT
Project-URL: Homepage, https://github.com/ElemTran/mcp-feedback-pipe
Project-URL: Repository, https://github.com/ElemTran/mcp-feedback-pipe
Project-URL: Documentation, https://github.com/ElemTran/mcp-feedback-pipe/blob/main/docs/
Project-URL: Bug Tracker, https://github.com/ElemTran/mcp-feedback-pipe/issues
Project-URL: Changelog, https://github.com/ElemTran/mcp-feedback-pipe/blob/main/RELEASE_NOTES.md
Keywords: mcp,feedback,web,ssh,flask,uvx,model-context-protocol
Classifier: Development Status :: 5 - Production/Stable
Classifier: Intended Audience :: Developers
Classifier: License :: OSI Approved :: MIT License
Classifier: Programming Language :: Python :: 3
Classifier: Programming Language :: Python :: 3.8
Classifier: Programming Language :: Python :: 3.9
Classifier: Programming Language :: Python :: 3.10
Classifier: Programming Language :: Python :: 3.11
Classifier: Programming Language :: Python :: 3.12
Classifier: Topic :: Software Development :: Libraries :: Python Modules
Classifier: Topic :: Internet :: WWW/HTTP :: WSGI :: Application
Classifier: Topic :: Scientific/Engineering :: Artificial Intelligence
Classifier: Environment :: Web Environment
Classifier: Framework :: Flask
Requires-Python: >=3.8
License-File: LICENSE
Requires-Dist: mcp>=1.9.0
Requires-Dist: flask>=3.0.0
Requires-Dist: flask-socketio>=5.3.0
Requires-Dist: eventlet>=0.33.0
Requires-Dist: pillow>=8.0.0
Requires-Dist: python-multipart>=0.0.20
Requires-Dist: python-dotenv>=1.0.0
Requires-Dist: uvicorn>=0.30.0
Requires-Dist: starlette>=0.40.0
Requires-Dist: sse-starlette>=2.0.0
Requires-Dist: requests>=2.25.0
Provides-Extra: dev
Requires-Dist: pytest>=7.0.0; extra == "dev"
Requires-Dist: pytest-cov>=4.0.0; extra == "dev"
Requires-Dist: pytest-asyncio>=0.21.0; extra == "dev"
Requires-Dist: black>=23.0.0; extra == "dev"
Requires-Dist: flake8>=6.0.0; extra == "dev"
Requires-Dist: mypy>=1.0.0; extra == "dev"
Provides-Extra: test
Requires-Dist: pytest>=7.0.0; extra == "test"
Requires-Dist: pytest-cov>=4.0.0; extra == "test"
Requires-Dist: pytest-asyncio>=0.21.0; extra == "test"
Dynamic: license-file
